markov_chain_reducer_soa/__init__.py
markov_chain_reducer_soa/link.py
markov_chain_reducer_soa/markov_chain_reducer.py
markov_chain_reducer_soa-1.0.2.dist-info/METADATA
markov_chain_reducer_soa-1.0.2.dist-info/WHEEL
markov_chain_reducer_soa-1.0.2.dist-info/top_level.txt
markov_chain_reducer_soa-1.0.2.dist-info/RECORD
