Metadata-Version: 2.1
Name: markov-chain-reducer-soa
Version: 1.0.2
Summary: Reduce Markov's chains
Author: StackCanary
